{
    "extends": ["tslint-react"],
    "rules": {
        "align": false,
        "ban": false,
        "class-name": false,
        "comment-format": false,
        "curly": false,
        "eofline": false,
        "forin": false,
        "indent": false,
        "interface-name": false,
        "jsdoc-format": false,
        "jsx-no-lambda": false,
        "jsx-no-multiline-js": false,
        "label-position": false,
        "max-line-length": false,
        "member-ordering": false,
        "no-any": false,
        "no-arg": false,
        "no-bitwise": false,
        "no-console": false,
        "no-consecutive-blank-lines": false,
        "no-construct": false,
        "no-debugger": false,
        "no-duplicate-variable": false,
        "no-empty": false,
        "no-eval": false,
        "no-shadowed-variable": false,
        "no-string-literal": false,
        "no-switch-case-fall-through": false,
        "no-trailing-whitespace": false,
        "no-unused-expression": false,
        "one-line": false,
        "quotemark": false,
        "radix": false,
        "semicolon": false,
        "switch-default": false,
        "trailing-comma": false,
        "triple-equals": false,
        "typedef": false,
        "typedef-whitespace": false,
        "variable-name": false,
        "whitespace": false
    }
}
